setup.cfg
setup.py
dots_backend/__init__.py
dots_backend/dots_analysis.py
dots_backend/dots_arrays.py
dots_backend/dots_plotting.py
dots_for_microarrays.egg-info/PKG-INFO
dots_for_microarrays.egg-info/SOURCES.txt
dots_for_microarrays.egg-info/dependency_links.txt
dots_for_microarrays.egg-info/requires.txt
dots_for_microarrays.egg-info/top_level.txt
dots_scripts/dots_workflow.py
dots_tests/__init__.py
dots_tests/test_dots_analysis.py
dots_tests/test_dots_arrays.py