Metadata-Version: 1.1
Name: dots-for-microarrays
Version: 0.2.0
Summary: Simple analysis of Agilent one-color arrays.
Home-page: https://github.com/sandyjmacdonald/dots_for_microarrays
Author: Sandy Macdonald
Author-email: sandyjmacdonald@gmail.com
License: MIT
Download-URL: https://github.com/sandyjmacdonald/dots_for_microarrays/tarball/v0.2.0
Keywords: bioinformatics,genomics,microarrays
Platform: UNKNOWN
Classifier: License :: OSI Approved :: MIT License
Classifier: Operating System :: Unix
Classifier: Operating System :: POSIX :: Linux
Classifier: Operating System :: MacOS :: MacOS X
Classifier: Programming Language :: Python :: 2.7
Classifier: Topic :: Software Development :: Libraries :: Python Modules
Classifier: Topic :: Scientific/Engineering :: Bio-Informatics
